{
  "Manoj Nair": {
    "Reporting Manager": "Vanashree Khedkar",
    "Team": "AU"
  },
  "Pradeep Naik": {
    "Reporting Manager": "Manoj Nair",
    "Team": "AU"
  },
  "Sharan Saraf": {
    "Reporting Manager": "Manoj Nair",
    "Team": "AU"
  },
  "Hoorbanu Sorathiya": {
    "Reporting Manager": "Sharan Saraf",
    "Team": "AU"
  },
  "Sagar Pingale": {
    "Reporting Manager": "Pradeep Naik",
    "Team": "AU"
  },
  "Navin Devrukhkar": {
    "Reporting Manager": "Pradeep Naik",
    "Team": "AU"
  },
  "Neha Sharma": {
    "Reporting Manager": "Pradeep Naik",
    "Team": "AU"
  },
  "Azharruddin Khan": {
    "Reporting Manager": "Pradeep Naik",
    "Team": "AU"
  },
  "Uday Ghule": {
    "Reporting Manager": "Pradeep Naik",
    "Team": "AU"
  },
  "Snehal More": {
    "Reporting Manager": "Sharan Saraf",
    "Team": "AU"
  },
  "Narayan Nadar": {
    "Reporting Manager": "Sharan Saraf",
    "Team": "AU"
  },
  "Swapnil Singh": {
    "Reporting Manager": "Sharan Saraf",
    "Team": "AU"
  },
  "Radhika Parkhi": {
    "Reporting Manager": "Sharan Saraf",
    "Team": "AU"
  },
  "Afzaal Shaikh": {
    "Reporting Manager": "Manoj Nair",
    "Team": "AU"
  },
  "Akhil Sawant": {
    "Reporting Manager": "Manoj Nair",
    "Team": "AU"
  },
  "Viral Jain": {
    "Reporting Manager": "Vanashree Khedkar",
    "Team": "INTL"
  },
  "Darryl Dmello": {
    "Reporting Manager": "Viral Jain",
    "Team": "INTL"
  },
  "Shoaib Shaikh": {
    "Reporting Manager": "Darryl Dmello",
    "Team": "INTL"
  },
  "Sudeep Dalal": {
    "Reporting Manager": "Darryl Dmello",
    "Team": "INTL"
  },
  "Ritesh kumar": {
    "Reporting Manager": "Darryl Dmello",
    "Team": "INTL"
  },
  "Uday Vikurthi": {
    "Reporting Manager": "Darryl Dmello",
    "Team": "INTL"
  },
  "Gilbert Chettiar": {
    "Reporting Manager": "Darryl Dmello",
    "Team": "INTL"
  },
  "Rehaan Rizvi": {
    "Reporting Manager": "Viral Jain",
    "Team": "INTL"
  },
  "Sanjay Panwar": {
    "Reporting Manager": "Viral Jain",
    "Team": "INTL"
  },
  "Sarosh Ahmad": {
    "Reporting Manager": "Viral Jain",
    "Team": "INTL"
  },
  "Mayur Mane": {
    "Reporting Manager": "Viral Jain",
    "Team": "INTL"
  },
  "Nitin Patel": {
    "Reporting Manager": "Rehaan Rizvi",
    "Team": "INTL"
  },
  "Chinmay Kalekar": {
    "Reporting Manager": "Rehaan Rizvi",
    "Team": "INTL"
  },
  "Deep Kothari": {
    "Reporting Manager": "Sanjay Panwar",
    "Team": "INTL"
  },
  "Thasaratha Nadar": {
    "Reporting Manager": "Sanjay Panwar",
    "Team": "INTL"
  },
  "Lavish Mundra": {
    "Reporting Manager": "Rehaan Rizvi",
    "Team": "INTL"
  },
  "Karan Shelar": {
    "Reporting Manager": "Mayur Mane",
    "Team": "INTL"
  },
  "Sagar Lund": {
    "Reporting Manager": "Mayur Mane",
    "Team": "INTL"
  },
  "Vishal Chauhan": {
    "Reporting Manager": "Rehaan Rizvi",
    "Team": "INTL"
  },
  "Azizuddin Syed": {
    "Reporting Manager": "Sanjay Panwar",
    "Team": "INTL"
  },
  "Riya Jena": {
    "Reporting Manager": "Rehaan Rizvi",
    "Team": "INTL"
  },
  "Subham Mahapatra": {
    "Reporting Manager": "Mayur Mane",
    "Team": "INTL"
  },
  "Akash Pohal": {
    "Reporting Manager": "Sarosh Ahmad",
    "Team": "INTL"
  },
  "Manali Talekar": {
    "Reporting Manager": "Mayur Mane",
    "Team": "INTL"
  },
  "Swati Dutta": {
    "Reporting Manager": "Rehaan Rizvi",
    "Team": "INTL"
  },
  "Jayaram Shetty": {
    "Reporting Manager": "Sanjay Panwar",
    "Team": "INTL"
  },
  "Suhbransu Nanda": {
    "Reporting Manager": "Vanashree Khedkar",
    "Team": "US"
  },
  "Sumit Korade": {
    "Reporting Manager": "Suhbransu Nanda",
    "Team": "US"
  },
  "Reema Binoy": {
    "Reporting Manager": "Sumit Korade",
    "Team": "US"
  },
  "Salman Patel": {
    "Reporting Manager": "Sumit Korade",
    "Team": "US"
  },
  "Shiju Joseph": {
    "Reporting Manager": "Sumit Korade",
    "Team": "US"
  },
  "Ashfaque Shaikh": {
    "Reporting Manager": "Sumit Korade",
    "Team": "US"
  },
  "Azim Salmani": {
    "Reporting Manager": "Sumit Korade",
    "Team": "US"
  },
  "Amruta Gokhale": {
    "Reporting Manager": "Sumit Korade",
    "Team": "US"
  },
  "Raashid Khan": {
    "Reporting Manager": "Sumit Korade",
    "Team": "US"
  },
  "Pavan Alur": {
    "Reporting Manager": "Sumit Korade",
    "Team": "US"
  },
  "Amarnath Gupta": {
    "Reporting Manager": "Sumit Korade",
    "Team": "US"
  },
  "Bhushan Chaudhari": {
    "Reporting Manager": "Sumit Korade",
    "Team": "US"
  },
  "Lokesh Akkala": {
    "Reporting Manager": "Sumit Korade",
    "Team": "US"
  },
  "Chaitanya Nawale": {
    "Reporting Manager": "Sumit Korade",
    "Team": "US"
  },
  "Chetan Boricha": {
    "Reporting Manager": "Sumit Korade",
    "Team": "US"
  },
  "Jayesh Singh": {
    "Reporting Manager": "Sumit Korade",
    "Team": "US"
  },
  "Riddhi Jambhekar": {
    "Reporting Manager": "Sumit Korade",
    "Team": "US"
  },
  "Abhishek Nishad": {
    "Reporting Manager": "Sumit Korade",
    "Team": "US"
  },
  "Steffani Dsouza": {
    "Reporting Manager": "Sumit Korade",
    "Team": "US"
  },
  "Sayantika Deb": {
    "Reporting Manager": "Sumit Korade",
    "Team": "US"
  },
  "Suresh Burra": {
    "Reporting Manager": "Sumit Korade",
    "Team": "US"
  },
  "Digvijay Pattnayak": {
    "Reporting Manager": "Sumit Korade",
    "Team": "US"
  },
  "Ashley Dsouza": {
    "Reporting Manager": "Sumit Korade",
    "Team": "US"
  },
  "Mohammed Sadiqh": {
    "Reporting Manager": "Sumit Korade",
    "Team": "US"
  },
  "Gautaman Narayanan": {
    "Reporting Manager": "Sumit Korade",
    "Team": "US"
  },
  "Vinod Bisht": {
    "Reporting Manager": "Sumit Korade",
    "Team": "US"
  },
  "Sejal Mahida": {
    "Reporting Manager": "Sumit Korade",
    "Team": "US"
  },
  "Siddhant Pandey": {
    "Reporting Manager": "Sumit Korade",
    "Team": "US"
  },
  "Sakshi Joshi": {
    "Reporting Manager": "Sumit Korade",
    "Team": "US"
  },
  "Senthil Kumaran": {
    "Reporting Manager": "Suhbransu Nanda",
    "Team": "US"
  }
}
